reddit_persona/__init__.py
reddit_persona/__main__.py
reddit_persona/go.py
reddit_persona/indicoKey.txt
reddit_persona/insights.py
reddit_persona/io_helper.py
reddit_persona/keycheck.py
reddit_persona/new.py
reddit_persona/reddit_creds.json
reddit_persona/reddit_get.py
reddit_persona/requirements.txt
reddit_persona/setup.py
reddit_persona/test.py
reddit_persona-1.2.22.dist-info/WHEEL
reddit_persona-1.2.22.dist-info/METADATA
reddit_persona-1.2.22.dist-info/RECORD
